[
    {
        "name": "GRASS",
        "type": "ENERGY"
    },
    {
        "name": "FIRE",
        "type": "ENERGY"
    },
    {
        "name": "WATER",
        "type": "ENERGY"
    },
    {
        "name": "LIGHTNING",
        "type": "ENERGY"
    },
    {
        "name": "PSYCHIC",
        "type": "ENERGY"
    },
    {
        "name": "DOUBLE_COLOURLESS",
        "type": "ENERGY"
    },


    {
        "name": "Staryu",
        "type": "POKEMON",
        "energyType": "water",
        "hp": 4,
        "preEvolution": null,
        "power": null,
        "resistance": {},
        "weakness": {},
        "moves": [
            {
                "name": "Slap",
                "description": "",
                "cost": ["WATER"],
                "actions": [
                    { "type": "APPLY_DAMAGE", "damage": 2 }
                ]
            }
        ]
    }
]